{
  "traces": [
    {
      "request_id": 0,
      "seq_prompt": 257,
      "seq_generate": 64,
      "total_latency_s": 16.241575956344604,
      "tokens_per_s": 3.940504306480127,
      "peak_alloc_bytes": 0,
      "peak_reserved_bytes": 0,
      "backend": "huggingface",
      "model": "facebook/opt-1.3b",
      "timestamp": 1757158365.554052,
      "error": null
    },
    {
      "request_id": 0,
      "seq_prompt": 257,
      "seq_generate": 64,
      "total_latency_s": 14.923783540725708,
      "tokens_per_s": 4.288456732526947,
      "peak_alloc_bytes": 0,
      "peak_reserved_bytes": 0,
      "backend": "huggingface",
      "model": "facebook/opt-1.3b",
      "timestamp": 1757158381.796149,
      "error": null
    },
    {
      "request_id": 1,
      "seq_prompt": 257,
      "seq_generate": 64,
      "total_latency_s": 15.07900094985962,
      "tokens_per_s": 4.244313016015549,
      "peak_alloc_bytes": 0,
      "peak_reserved_bytes": 0,
      "backend": "huggingface",
      "model": "facebook/opt-1.3b",
      "timestamp": 1757158396.7200556,
      "error": null
    },
    {
      "request_id": 0,
      "seq_prompt": 257,
      "seq_generate": 64,
      "total_latency_s": 15.193792581558228,
      "tokens_per_s": 4.212246524786793,
      "peak_alloc_bytes": 0,
      "peak_reserved_bytes": 0,
      "backend": "huggingface",
      "model": "facebook/opt-1.3b",
      "timestamp": 1757158411.799539,
      "error": null
    },
    {
      "request_id": 1,
      "seq_prompt": 257,
      "seq_generate": 64,
      "total_latency_s": 15.20125961303711,
      "tokens_per_s": 4.21017742142312,
      "peak_alloc_bytes": 0,
      "peak_reserved_bytes": 0,
      "backend": "huggingface",
      "model": "facebook/opt-1.3b",
      "timestamp": 1757158426.9934783,
      "error": null
    },
    {
      "request_id": 2,
      "seq_prompt": 257,
      "seq_generate": 64,
      "total_latency_s": 15.072370052337646,
      "tokens_per_s": 4.246180247549982,
      "peak_alloc_bytes": 0,
      "peak_reserved_bytes": 0,
      "backend": "huggingface",
      "model": "facebook/opt-1.3b",
      "timestamp": 1757158442.194884,
      "error": null
    },
    {
      "request_id": 3,
      "seq_prompt": 257,
      "seq_generate": 64,
      "total_latency_s": 19.825872659683228,
      "tokens_per_s": 3.228105067483197,
      "peak_alloc_bytes": 0,
      "peak_reserved_bytes": 0,
      "backend": "huggingface",
      "model": "facebook/opt-1.3b",
      "timestamp": 1757158457.267371,
      "error": null
    }
  ],
  "metrics": {
    "total_requests": 7,
    "successful_requests": 7,
    "failed_requests": 0,
    "error_rate": 0.0,
    "mean_latency_s": 15.933950764792305,
    "min_latency_s": 14.923783540725708,
    "max_latency_s": 19.825872659683228,
    "p50_latency_s": 15.193792581558228,
    "p95_latency_s": 19.825872659683228,
    "p99_latency_s": 19.825872659683228,
    "mean_tokens_per_s": 4.0528547594665305,
    "total_tokens_per_s": 28.369983316265714,
    "min_tokens_per_s": 3.228105067483197,
    "max_tokens_per_s": 4.288456732526947,
    "peak_alloc_bytes": 0,
    "peak_reserved_bytes": 0,
    "peak_alloc_gb": 0.0,
    "peak_reserved_gb": 0.0,
    "mean_alloc_bytes": 0.0,
    "mean_reserved_bytes": 0.0
  },
  "timestamp": 1757158477.0936515
}